{
  "name": "AwesomeJob",
  "types": [{
      "name": "PriceData",
      "fields": [
        { "name": "dataIndex", "type": "long" },
        { "name": "open", "type": "float" },
        { "name": "high", "type": "float" },
        { "name": "low", "type": "float" },
        { "name": "close", "type": "float" }
      ]
    }],
  "functions": [{
    "name": "test_donothing",
    "arguments": [
      { "name": "range", "type": "int", "argType": "in" },
      { "name": "realSize", "type": "int", "argType": "in" },
      { "name": "inBuffer", "type": { "arrayType": "PriceData" }, "memoryType": "global", "argType": "in" },
      { "name": "outBuffer", "type": { "arrayType": "PriceData" }, "memoryType": "global", "argType": "out" }
    ]
  }, {
    "name": "test_donothing2",
    "arguments": [
      { "name": "inBuffer", "type": { "arrayType": "PriceData" }, "memoryType": "global", "argType": "in" },
      { "name": "outBuffer", "type": { "arrayType": "PriceData" }, "memoryType": "global", "argType": "out" }
    ]
  }]
}
